AudioFileTranslator_S2ST/ReplaceVideoAudio.py
AudioFileTranslator_S2ST/__init__.py
AudioFileTranslator_S2ST/audio_translator.py
AudioFileTranslator_S2ST/main.py
AudioFileTranslator_S2ST/sentence_translator.py
AudioFileTranslator_S2ST/translator_gui.py
AudioFileTranslator_S2ST/youtube_downloader.py
audio_file_translator-2.1.dist-info/LICENSE
audio_file_translator-2.1.dist-info/METADATA
audio_file_translator-2.1.dist-info/WHEEL
audio_file_translator-2.1.dist-info/entry_points.txt
audio_file_translator-2.1.dist-info/top_level.txt
audio_file_translator-2.1.dist-info/RECORD
