Metadata-Version: 2.1
Name: audio-file-translator
Version: 2.1
Summary: audio-file-translator. For Windows, macOS, and Linux, on Python 3
Home-page: https://github.com/overcrash66/Audio-File-Translator---S2ST
Author: Wael SAHLI
Author-email: speech2speechtranslation@gmail.com
License: MIT
Keywords: gui audio video translator
Platform: UNKNOWN
License-File: LICENSE
Requires-Dist: Pillow
Requires-Dist: pygame
Requires-Dist: transformers
Requires-Dist: gtts
Requires-Dist: torchaudio
Requires-Dist: pydub
Requires-Dist: pytube
Requires-Dist: librosa
Requires-Dist: torch
Requires-Dist: customtkinter
Requires-Dist: httpx
Requires-Dist: CTkMenuBar
